larpix/__init__.py
larpix/bitarrayhelper.py
larpix/chip.py
larpix/controller.py
larpix/key.py
larpix/larpix.py
larpix/configs/__init__.py
larpix/configs/chip/__init__.py
larpix/configs/chip/csa_bypass.json
larpix/configs/chip/default.json
larpix/configs/chip/default_lightpix_v1.json
larpix/configs/chip/default_v2.json
larpix/configs/chip/default_v2b.json
larpix/configs/chip/physics.json
larpix/configs/chip/quiet.json
larpix/configs/controller/__init__.py
larpix/configs/controller/bare-die-v2-v1.0.0.json
larpix/configs/controller/lightpix_v1_example.json
larpix/configs/controller/network-3x3-tile-channel0.json
larpix/configs/controller/network-3x3-tile-channel1.json
larpix/configs/controller/network-3x3-tile-channel2.json
larpix/configs/controller/pcb-10_chip_info.json
larpix/configs/controller/pcb-1_chip_info.json
larpix/configs/controller/pcb-2_chip_info.json
larpix/configs/controller/pcb-3_chip_info.json
larpix/configs/controller/pcb-4_chip_info.json
larpix/configs/controller/pcb-5_chip_info.json
larpix/configs/controller/pcb-6_chip_info.json
larpix/configs/controller/v2_example.json
larpix/configs/io/__init__.py
larpix/configs/io/daq-srv1.json
larpix/configs/io/daq-srv2.json
larpix/configs/io/daq-srv3.json
larpix/configs/io/daq-srv4.json
larpix/configs/io/daq-srv5.json
larpix/configs/io/daq-srv6.json
larpix/configs/io/daq-srv7.json
larpix/configs/io/default.json
larpix/configs/io/loopback.json
larpix/configs/io/pacman.json
larpix/configuration/__init__.py
larpix/configuration/configuration.py
larpix/configuration/configuration_lightpix_v1.py
larpix/configuration/configuration_v1.py
larpix/configuration/configuration_v2.py
larpix/configuration/configuration_v2_base.py
larpix/configuration/configuration_v2b.py
larpix/format/__init__.py
larpix/format/hdf5format.py
larpix/format/message_format.py
larpix/format/pacman_msg_format.py
larpix/format/rawhdf5format.py
larpix/io/__init__.py
larpix/io/fakeio.py
larpix/io/io.py
larpix/io/multizmq_io.py
larpix/io/pacman_io.py
larpix_control-3.7.0.dist-info/LICENSE.txt
larpix_control-3.7.0.dist-info/METADATA
larpix_control-3.7.0.dist-info/WHEEL
larpix_control-3.7.0.dist-info/top_level.txt
larpix_control-3.7.0.dist-info/RECORD
