Metadata-Version: 2.1
Name: larpix-control
Version: 3.7.0
Summary: Control the LArPix chip
Home-page: https://github.com/larpix/larpix-control
Author: Peter Madigan and Sam Kohn
Author-email: pmadigan@lbl.gov
License: Other/Proprietary License
Keywords: dune physics
Platform: UNKNOWN
Classifier: Development Status :: 4 - Beta
Classifier: Intended Audience :: Science/Research
Classifier: Programming Language :: Python :: 3
License-File: LICENSE.txt
Requires-Dist: pyserial (>=3.4)
Requires-Dist: pytest (>=6.2)
Requires-Dist: bitarray (>=0.8)
Requires-Dist: pyzmq (>=18.0)
Requires-Dist: sphinx-rtd-theme (>=0.5)
Requires-Dist: numpy (>=1.16)
Requires-Dist: h5py (>=3.1)
Requires-Dist: bidict (>=0.18.0)
Requires-Dist: networkx (>=2.2)
